silverbots/__init__.py
silverbots/slack.py
silverbots/telegram.py
silverbots-0.1.2.dist-info/LICENSE
silverbots-0.1.2.dist-info/METADATA
silverbots-0.1.2.dist-info/WHEEL
silverbots-0.1.2.dist-info/top_level.txt
silverbots-0.1.2.dist-info/RECORD
