Metadata-Version: 2.1
Name: silverbots
Version: 0.1.2
Summary: Silver Bots
Home-page: https://github.com/WwWSrJSilverWwW/SilverBots
Author: SrJSilver
Author-email: Sergey081203@ya.ru
License: UNKNOWN
Platform: UNKNOWN
Classifier: Programming Language :: Python :: 3
Classifier: License :: OSI Approved :: MIT License
Classifier: Operating System :: OS Independent
Requires-Python: >=3.6
License-File: LICENSE
Requires-Dist: requests (>=2.26.0)
